{"state":{"nodes":[{"id":"track_in-1780846081916","type":"track_in","params":{},"position":{"x":2078.6922544260474,"y":-1202.4056728691262}},{"id":"noisecraft_source-1780846087093","type":"noisecraft_source","label":"NoiseCraft","params":{"patchFile":"nc_noise_patch.ncft","gain":1},"position":{"x":2077.1922544260474,"y":-1324.4056728691262}},{"id":"destination-1780846248332","type":"destination","label":"Speaker Out","params":{},"position":{"x":2447.4840070409905,"y":-1045.4094503967426}},{"id":"destination-1780847118605","type":"destination","label":"Speaker Out","params":{},"position":{"x":2568.6838226771597,"y":-1248.9075616329344}}],"edges":[{"id":"e-track_in-1780846081916-destination-1780846248332-1780846250259","source":"track_in-1780846081916","sourceHandle":"out","target":"destination-1780846248332","targetHandle":"in"},{"id":"e-noisecraft_source-1780846087093-destination-1780847118605-1780847120428","source":"noisecraft_source-1780846087093","sourceHandle":"out","target":"destination-1780847118605","targetHandle":"in"}]},"version":0}